<?xml version="1.0" encoding="utf-8"?>
<?xml-stylesheet type="text/xsl" href="cda.xsl"?> 
  <!-- 		
    Title: QDM Based QRDA V6 Good sample
    Author: Michael Holck
    Date:   07-21-2017 	
    Update: 03-09-2018 Removed trigger for 4388-16595 as it is a "MAY such that" rather than a SHOULD
    Update: 09-25-2018 for STU 5.1
            JIRA: https://tracker.esacinc.com/browse/QRDA-460
    Update: 10-22-2018 QRDA-501  Added test for 3343-17081
            JIRA: https://tracker.esacinc.com/browse/QRDA-501
    
    Total Errors Expected: 23
        Failure a-4388-12972-error SHALL contain exactly one [1..1] templateId (CONF:4388-12972) such that it SHALL contain exactly one [1..1] @root="2.16.840.1.113883.10.20.24.1.2" (CONF:4388-26943). SHALL contain exactly one [1..1] @extension="2018-10-01" (CONF:4388-28696)
        Failure a-4388-16598-error SHALL contain exactly one [1..1] recordTarget (CONF:4388-16598)
        Failure a-4388-16600-error SHALL contain exactly one [1..1] custodian
        Failure a-4388-12973-error SHALL contain exactly one [1..1] component (CONF:4388-12973) 
        Failure a-4388-16856-error recordTarget SHALL contain exactly one [1..1] patientRole (CONF:4388-16856)
        Failure a-4388-27570-error patientRole SHALL contain exactly one [1..1] patient (CONF:4388-27570)
        Failure a-4388-27571-error patient SHALL contain exactly one [1..1] birthTime (CONF:4388-27571)
        Failure a-4388-27572-error patient SHALL contain exactly one [1..1] administrativeGenderCode (CONF:4388-27572)
        Failure a-4388-27573-error patient SHALL contain exactly one [1..1] raceCode (CONF:4388-27573
        Failure a-4388-27574-error patient SHALL contain exactly one [1..1] ethnicGroupCode (CONF:4388-27574)
        Failure a-4388-28239-error custodian SHALL contain exactly one [1..1] assignedCustodian (CONF:4388-28239)
        Failure a-4388-28240-error assignedCustodian SHALL contain exactly one [1..1] representedCustodianOrganization (CONF:4388-28240)
    	  Failure a-4388-16704-error The informationRecipient, if present, SHALL contain exactly one [1..1] intendedRecipient (CONF:4388-16704)
        Failure a-4388-16705-error intendedRecipient SHALL contain at least one [1..*] id (CONF:4388-16705)
        Failure a-4388-16581-error This serviceEvent SHALL contain exactly one [1..1] @classCode="PCPR" Care Provision (CONF:4388-16581).
    	  Failure a-4388-16583-error This serviceEvent SHALL contain at least one [1..*] performer (CONF:4388-16583).
    	  Failure a-4388-16584-error Such performers SHALL contain exactly one [1..1] @typeCode="PRF" Performer (CONF:4388-16584).
    	  Failure a-4388-16586-error Such performers SHALL contain exactly one [1..1] assignedEntity (CONF:4388-16586).
    	  Failure a-4388-16591-error This assignedEntity SHALL contain exactly one [1..1] representedOrganization (CONF:4388-16591).
    	  Failure a-4388-17018-error Component SHALL contain exactly one [1..1] structuredBody (CONF:4388-17081)
    	  Failure a-4388-17082-error structuredBody SHALL contain exactly one [1..1] component (CONF:4388-17082) such that This component SHALL contain exactly one [1..1] Measure Section QDM (identifier: urn:oid:2.16.840.1.113883.10.20.24.2.3) (CONF:4388-17083)
    	  Failure a-4388-17090-error structuredBody SHALL contain exactly one [1..1] component (CONF:4388-17090) such that This component SHALL contain exactly one [1..1] Reporting Parameters Section (identifier: urn:oid:2.16.840.1.113883.10.20.17.2.1) (CONF:4388-17092)
    	  Failure a-4388-17091-error structuredBody SHALL contain exactly one [1..1] component (CONF:4388-17091) such that This component SHALL contain exactly one [1..1] Patient Data Section QDM (V5) (identifier: urn:hl7ii:2.16.840.1.113883.10.20.24.2.1:2018-10-01) (CONF:4388-17093)
   
    Total Warnings Expected: 1
        Warning a-4388-16592-warning representedOrganization SHOULD contain zero or one [0..1] id (CONF:4388-16592) such that it SHALL contain exactly one [1..1] @root="2.16.840.1.113883.4.2" Tax ID Number (CONF:4388-16593)
 
  -->

<ClinicalDocument xmlns:xsi="http://www.w3.org/2001/XMLSchema-instance"
  xsi:schemaLocation="urn:hl7-org:v3 ../Schema/CDA/infrastructure/cda/CDA_SDTC.xsd" xmlns="urn:hl7-org:v3"
  xmlns:voc="urn:hl7-org:v3/voc" xmlns:sdtc="urn:hl7-org:sdtc">
  <!-- QDM-Based QRDA (V6) -->
  <templateId root="2.16.840.1.113883.10.20.24.1.2" extension="2018-10-01"/>
  <!-- Failure a-4388-12972-error Multiple root templateIds -->
  <templateId root="2.16.840.1.113883.10.20.24.1.2" extension="2018-10-01"/>
  
  <recordTarget>
    <patientRole>
      <!-- This is the patient's Medical HIC number -->
      <id extension="111223333A" root="2.16.840.1.113883.4.572"/>
      <!-- This is the patient's Medical Beneficiary Identifier (MBI) number -->
      <id extension="234567890" root="2.16.840.1.113883.4.927"/>
       <patient>
        <administrativeGenderCode code="F" codeSystem="2.16.840.1.113883.5.1"/>
        <birthTime value="20020201"/>
        <raceCode code="2106-3" codeSystem="2.16.840.1.114222.4.11.836" displayName="White"/>
        <ethnicGroupCode code="2186-5" codeSystem="2.16.840.1.114222.4.11.837"
          displayName="Not Hispanic or Latino"/>
       </patient>
    </patientRole>
  </recordTarget>
 
  <!-- Failure a-4388-16598-error Zero or Multiple record targets -->
  <recordTarget>
    <patientRole>
      <id extension="111223333A" root="2.16.840.1.113883.4.572"/>
      <!-- Failure a-4388-27570-error Missing or multiple patients in patientRole -->
    </patientRole>
    <!-- Failure a-4388-16856-error Zero or Multiple patient roles in recordTarget-->
    <patientRole>
      <id extension="111223333A" root="2.16.840.1.113883.4.572"/>
      <patient>
        <!-- Failure a-4388-27571-error Missing or multiple birthTime in patient -->
        <!-- Failure a-4388-27572-error Missing or multiple administrativeGenderCode in patient-->
        <!-- Failure a-4388-27573-error Missing or multiple raceCode in patient -->
        <raceCode code="2106-3" codeSystem="2.16.840.1.114222.4.11.836" displayName="White"/>
        <raceCode code="2106-3" codeSystem="2.16.840.1.114222.4.11.836" displayName="White"/>
        <!-- Failure a-4388-27574-error Missing or multiple ethnicGroupcode in patient -->
      </patient>
    </patientRole>
  </recordTarget>
  
  <custodian>
    <assignedCustodian>
      <representedCustodianOrganization>
        <!-- CMS Certification Number -->
        <id root="2.16.840.1.113883.4.336" extension="1111111"/>
        <!-- Tax ID Number -->
        <id root="2.16.840.1.113883.4.2" extension="2222222"/>
        <!-- Joint Commission's Health Care Organization (HCO) -->
        <id root="1.3.6.1.4.1.33895" extension="3333333"/>
      </representedCustodianOrganization>
      
      <!-- Failure a-4388-28240-error Missing or multiple representedCustodianOrganization in assignedCustodian -->
      <representedCustodianOrganization/>
    </assignedCustodian>
  </custodian>
  
  <!-- Failure a-4388-16600-error Zero or Multiple custodians -->
  <custodian>
    <!-- Failure a-4388-28239-error Missing or Multiple assignedCustodian in custodian -->
  </custodian>
  
  <informationRecipient>
    <intendedRecipient>
      <id root="2.16.840.1.113883.4.6" extension="111111111"/>
      <receivedOrganization>
        <name>The DoctorsApart Physician Group</name>
      </receivedOrganization>
    </intendedRecipient>
    <!-- Failure a-4388-16704-error Missing or Multiple intendedRecipient in informationRecipient -->
    <intendedRecipient>
      <!-- a-4388-16705-error Missing id in intendedRecipient -->
    </intendedRecipient>
  </informationRecipient>
  
  <documentationOf typeCode="DOC">
    <serviceEvent classCode="PCPR">
       <!-- You can include multiple performers, each with an NPI, TIN, CCN. -->
      <performer typeCode="PRF">
        <assignedEntity>
          <!-- This is the provider NPI -->
          <id root="2.16.840.1.113883.4.6" extension="111111111"/>
          <representedOrganization>
            <!-- This is the organization TIN -->
            <id root="2.16.840.1.113883.4.2" extension="1234567"/>
            <!-- This is the organization CCN -->
            <id root="2.16.840.1.113883.4.336" extension="654321"/>
          </representedOrganization>
        </assignedEntity>
      </performer>
    </serviceEvent>
  </documentationOf>
  
  <documentationOf typeCode="DOC">
    <serviceEvent classCode='PCPR'>
      <!-- You can include multiple performers, each with an NPI, TIN, CCN. -->
      <performer typeCode="PRF">
        <assignedEntity>
          <!-- This is the provider NPI -->
          <id root="2.16.840.1.113883.4.6" extension="111111111"/>
          <representedOrganization>
            <!-- This is the organization TIN -->
            <id root="2.16.840.1.113883.4.2" extension="1234567"/>
            <!-- This is the organization CCN -->
            <id root="2.16.840.1.113883.4.336" extension="654321"/>
          </representedOrganization>
          
          <!-- Failure a-4388-16591-error Zero or Multiple representedOrganization -->
          <!-- Warning a-4388-16592-warning representedOrganization SHOULD contain zero or one [0..1] id (CONF:4388-16592) such that it SHALL contain exactly one [1..1] @root="2.16.840.1.113883.4.2" Tax ID Number (CONF:4388-16593) -->
          <representedOrganization/>
          
        </assignedEntity>
      </performer>
      <!-- Failure a-4388-16584-error performer missing @typeCode='PRF' -->
      <performer>
        <!-- Failure a-4388-16586-error Zero or multiple assignedEntity -->
      </performer>
    </serviceEvent>
  </documentationOf>
  
  <documentationOf>
    <!-- Failure a-4388-16581-error serviceEvent missing classCode='PCPR' -->
    <serviceEvent>
      <!-- Failure a-4388-16583-error Zero performer -->
    </serviceEvent>
  </documentationOf>
  
  <!-- QRDA Body -->
  <component>
    <structuredBody>
      <component>
        <section>
          <!-- 						 
            ***************************************************************** 						 
            Measure Section 						
            ***************************************************************** 					 
          -->
          <!-- This is the templateId for Measure Section -->
          <templateId root="2.16.840.1.113883.10.20.24.2.2"/>
          <!-- This is the templateId for Measure Section QDM -->
          <templateId root="2.16.840.1.113883.10.20.24.2.3"/>
        </section>
      </component>
      <!-- 				 
        ***************************************************************** 				 
        Reporting Parameters Section 				 
        ***************************************************************** 			 
      -->
      <component>
        <section>
          <!-- This is the templateId for Reporting Parameters section -->
          <templateId root="2.16.840.1.113883.10.20.17.2.1"/>
        </section>
      </component>
      <!-- 				 
        ***************************************************************** 				 
        Patient Data Section QDM (V5) 				 
        ***************************************************************** 			 
      -->
      <component>
        <section>
          <!-- Patient Data Section -->
          <templateId root="2.16.840.1.113883.10.20.17.2.4"/>
          <!-- Patient Data Section QDM (V5) -->
          <templateId root="2.16.840.1.113883.10.20.24.2.1" extension="2018-10-01"/>
        </section>
      </component>
    </structuredBody>
    
    <!-- Failure a-3343-17081-error Component SHALL contain exactly one [1..1] structuredBody (CONF:3343-17081) -->
    <structuredBody>
      <component>
        <section>
          <!-- 						 
            ***************************************************************** 						 
            Measure Section 						
            ***************************************************************** 					 
          -->
          <!-- This is the templateId for Measure Section -->
          <templateId root="2.16.840.1.113883.10.20.24.2.2"/>
          <!-- This is the templateId for Measure Section QDM -->
          <templateId root="2.16.840.1.113883.10.20.24.2.3"/>
        </section>
      </component>
      <!-- 				 
        ***************************************************************** 				 
        Reporting Parameters Section 				 
        ***************************************************************** 			 
      -->
      <component>
        <section>
          <!-- This is the templateId for Reporting Parameters section -->
          <templateId root="2.16.840.1.113883.10.20.17.2.1"/>
        </section>
      </component>
      <!-- 				 
        ***************************************************************** 				 
        Patient Data Section QDM (V5) 				 
        ***************************************************************** 			 
      -->
      <component>
        <section>
          <!-- Patient Data Section -->
          <templateId root="2.16.840.1.113883.10.20.17.2.4"/>
          <!-- Patient Data Section QDM (V5) -->
          <templateId root="2.16.840.1.113883.10.20.24.2.1" extension="2018-10-01"/>
        </section>
      </component>
    </structuredBody>    
  </component>
  
  <!-- Failure a-4388-12973-error Zero or Multiple component -->
  <component>
    <structuredBody>
      <!-- Failure a-4388-17082-error Zero or multiple Measure section -->
      <!-- Failure a-4388-17090-error Zero or multiple Reporting Parameters Section -->
      <!-- Failure a-4388-17091-error Zero or multiple Patient Data section -->
    </structuredBody>
  </component>

</ClinicalDocument>